ElectronicsCalculator/__init__.py
ElectronicsCalculator/electronics_calculator.py
ElectronicsCalculator/scale_factors.py
ElectronicsCalculator-0.3.dist-info/LICENSE
ElectronicsCalculator-0.3.dist-info/METADATA
ElectronicsCalculator-0.3.dist-info/WHEEL
ElectronicsCalculator-0.3.dist-info/top_level.txt
ElectronicsCalculator-0.3.dist-info/RECORD
