Metadata-Version: 2.1
Name: ElectronicsCalculator
Version: 0.3
Summary: Python module that provides methods to perform common electronics calculations.
Home-page: https://github.com/mino827/ElectronicsCalculator
Author: Mino Girimonti
Author-email: mino827@protonmail.com
License: GPL v3.0
Project-URL: Bug Tracker, https://github.com/mino827/ElectronicsCalculator/issues
Keywords: electronics,electrical,engineering,formula,formulae,calculation
Platform: UNKNOWN
Classifier: Programming Language :: Python :: 3
Classifier: License :: OSI Approved :: GNU General Public License v3 (GPLv3)
Classifier: Operating System :: OS Independent
Requires-Python: >=3.6
License-File: LICENSE
